bydantic/__init__.py
bydantic/core.py
bydantic/utils.py
bydantic-0.1.0.dist-info/licenses/LICENSE
bydantic-0.1.0.dist-info/METADATA
bydantic-0.1.0.dist-info/WHEEL
bydantic-0.1.0.dist-info/top_level.txt
bydantic-0.1.0.dist-info/RECORD
