Metadata-Version: 2.4
Name: bydantic
Version: 0.1.0
Summary: A type-aware bitfield serializing / deserializing library for Python
Author-email: Kyle Husmann <bydantic@kylehusmann.com>
License: Apache-2.0
Project-URL: Homepage, https://github.com/khusmann/bydantic
Project-URL: Bug Tracker, https://github.com/khusmann/bydantic/issues
Classifier: Programming Language :: Python :: 3
Classifier: License :: OSI Approved :: Apache Software License
Classifier: Operating System :: OS Independent
Classifier: Intended Audience :: Developers
Classifier: Topic :: Software Development :: Libraries
Classifier: Topic :: System :: Hardware
Requires-Python: >=3.10
License-File: LICENSE
Requires-Dist: typing_extensions>=4.1.0
Dynamic: license-file
